joystick_diagrams/__init__.py
joystick_diagrams/__main__.py
joystick_diagrams/app_init.py
joystick_diagrams/app_state.py
joystick_diagrams/config.py
joystick_diagrams/db/__init__.py
joystick_diagrams/db/db_bind_text.py
joystick_diagrams/db/db_device_management.py
joystick_diagrams/db/db_init.py
joystick_diagrams/db/db_plugin_data.py
joystick_diagrams/db/db_profile_parents.py
joystick_diagrams/db/db_profiles.py
joystick_diagrams/db/db_settings.py
joystick_diagrams/exceptions.py
joystick_diagrams/export.py
joystick_diagrams/export_device.py
joystick_diagrams/input/__init__.py
joystick_diagrams/input/axis.py
joystick_diagrams/input/button.py
joystick_diagrams/input/device.py
joystick_diagrams/input/hat.py
joystick_diagrams/input/input.py
joystick_diagrams/input/modifier.py
joystick_diagrams/input/profile.py
joystick_diagrams/input/profile_collection.py
joystick_diagrams/plugin_manager.py
joystick_diagrams/plugin_wrapper.py
joystick_diagrams/plugins/__init__.py
joystick_diagrams/plugins/dcs_world_plugin/__init__.py
joystick_diagrams/plugins/dcs_world_plugin/config.py
joystick_diagrams/plugins/dcs_world_plugin/dcs_world.py
joystick_diagrams/plugins/dcs_world_plugin/dcs_world_yacc.py
joystick_diagrams/plugins/dcs_world_plugin/img/dcs.ico
joystick_diagrams/plugins/dcs_world_plugin/lextab.py
joystick_diagrams/plugins/dcs_world_plugin/main.py
joystick_diagrams/plugins/dcs_world_plugin/settings.json
joystick_diagrams/plugins/Example/example_plugin/config.py
joystick_diagrams/plugins/Example/example_plugin/img/logo.ico
joystick_diagrams/plugins/Example/example_plugin/main.py
joystick_diagrams/plugins/Example/example_plugin/settings.json
joystick_diagrams/plugins/joystick_gremlin_plugin/__init__.py
joystick_diagrams/plugins/joystick_gremlin_plugin/config.py
joystick_diagrams/plugins/joystick_gremlin_plugin/img/jg.ico
joystick_diagrams/plugins/joystick_gremlin_plugin/joystick_gremlin.py
joystick_diagrams/plugins/joystick_gremlin_plugin/main.py
joystick_diagrams-2.0.9.dist-info/entry_points.txt
joystick_diagrams-2.0.9.dist-info/LICENSE
joystick_diagrams-2.0.9.dist-info/METADATA
joystick_diagrams-2.0.9.dist-info/WHEEL
joystick_diagrams-2.0.9.dist-info/RECORD
