Metadata-Version: 2.1
Name: joystick_diagrams
Version: 2.0.9
Summary: 
Home-page: https://www.joystick-diagrams.com
Author: Robert Cox
Requires-Python: >=3.11,<3.13
Classifier: Programming Language :: Python :: 3
Classifier: Programming Language :: Python :: 3.11
Classifier: Programming Language :: Python :: 3.12
Requires-Dist: dynaconf (>=3.2.4,<4.0.0)
Requires-Dist: ply (>=3.11,<4.0)
Requires-Dist: pre-commit (>=3.6.0,<4.0.0)
Requires-Dist: pyside6 (>=6.6.1,<7.0.0)
Requires-Dist: qt-material (>=2.14,<3.0)
Requires-Dist: qtawesome (>=1.3.0,<2.0.0)
Requires-Dist: requests (>=2.31.0,<3.0.0)
Requires-Dist: semver (>=3.0.2,<4.0.0)
Project-URL: Repository, https://github.com/Rexeh/joystick-diagrams
